rt_factory/__init__.py
rt_factory/cli.py
rt_factory/rt_factory.py
rt_factory-0.1.0.dist-info/DESCRIPTION.rst
rt_factory-0.1.0.dist-info/METADATA
rt_factory-0.1.0.dist-info/RECORD
rt_factory-0.1.0.dist-info/WHEEL
rt_factory-0.1.0.dist-info/entry_points.txt
rt_factory-0.1.0.dist-info/metadata.json
rt_factory-0.1.0.dist-info/top_level.txt
