Metadata-Version: 2.0
Name: rt-factory
Version: 0.1.0
Summary: Pythonic wrapper for the artifactory API
Home-page: https://github.com/melexis/rt_factory
Author: Peter Tillemans
Author-email: pti@melexis.com
License: Apache Software License 2.0
Keywords: rt_factory
Platform: UNKNOWN
Classifier: Development Status :: 2 - Pre-Alpha
Classifier: Intended Audience :: Developers
Classifier: License :: OSI Approved :: Apache Software License
Classifier: Natural Language :: English
Classifier: Programming Language :: Python :: 2
Classifier: Programming Language :: Python :: 2.6
Classifier: Programming Language :: Python :: 2.7
Classifier: Programming Language :: Python :: 3
Classifier: Programming Language :: Python :: 3.3
Classifier: Programming Language :: Python :: 3.4
Classifier: Programming Language :: Python :: 3.5
Classifier: Topic :: System :: Archiving :: Packaging
Classifier: Topic :: System :: Software Distribution
Requires-Dist: Click (>=6.0)
Requires-Dist: requests (>=2.12.0)
